udmi/__init__.py
udmi/base.py
udmi/config.py
udmi/discovery.py
udmi/logentry.py
udmi/metadata.py
udmi/pointset.py
udmi/properties.py
udmi/state.py
udmi/schemata/daq/schemas/udmi/common.json
udmi/schemata/daq/schemas/udmi/config.json
udmi/schemata/daq/schemas/udmi/config_gateway.json
udmi/schemata/daq/schemas/udmi/config_localnet.json
udmi/schemata/daq/schemas/udmi/config_pointset.json
udmi/schemata/daq/schemas/udmi/config_system.json
udmi/schemata/daq/schemas/udmi/discover.json
udmi/schemata/daq/schemas/udmi/discovery.json
udmi/schemata/daq/schemas/udmi/envelope.json
udmi/schemata/daq/schemas/udmi/event_pointset.json
udmi/schemata/daq/schemas/udmi/event_system.json
udmi/schemata/daq/schemas/udmi/logentry.json
udmi/schemata/daq/schemas/udmi/metadata.json
udmi/schemata/daq/schemas/udmi/metadata_cloud.json
udmi/schemata/daq/schemas/udmi/metadata_gateway.json
udmi/schemata/daq/schemas/udmi/metadata_localnet.json
udmi/schemata/daq/schemas/udmi/metadata_pointset.json
udmi/schemata/daq/schemas/udmi/metadata_system.json
udmi/schemata/daq/schemas/udmi/pointset.json
udmi/schemata/daq/schemas/udmi/properties.json
udmi/schemata/daq/schemas/udmi/state.json
udmi/schemata/daq/schemas/udmi/state_gateway.json
udmi/schemata/daq/schemas/udmi/state_pointset.json
udmi/schemata/daq/schemas/udmi/state_system.json
udmi/schemata/daq/schemas/udmi/units.json
udmi/tests/__init__.py
udmi/tests/test_udmi_schemata.py
pyudmi-0.0.6.dist-info/LICENSE
pyudmi-0.0.6.dist-info/METADATA
pyudmi-0.0.6.dist-info/WHEEL
pyudmi-0.0.6.dist-info/top_level.txt
pyudmi-0.0.6.dist-info/RECORD
