Metadata-Version: 2.1
Name: pyudmi
Version: 0.0.6
Summary: Helper classes for working with udmi
Home-page: https://github.com/arupiot/pyudmi.git
Author: Paul Harter
Author-email: paul@glowinthedark.co.uk
License: LICENSE
Platform: UNKNOWN
Requires-Dist: pytz
Requires-Dist: fastjsonschema
